Workbook

Sheet CONTROL DE CAMBIOS
A1: CONTROL DE CAMBIOS
A2: =+' INTERESADOS Y REQUISITOS'!A2 -> Proyecto…
A6: Versión | B6: Fecha | C6: Documento | D6: Autor | E6: Descripción del Cambio
A7: 1.01 | B7: 42748 | C7: Plan de Gestión del Proyecto | D7: Director de Proyecto | E7: Documento preliminar completo para entregar a Oficina de Proyectos
A12: Observaciones:
A13: El número principal del documento se modifica sólo cuando se registran cambios significativos referentes a tiempos, costos o alcance del proyecto.
A14: El número secundario de la versión del documento se modifica cuando se producen actualizaciones del mismo.

Sheet  INTERESADOS Y REQUISITOS
A1: GRILLA DE INTERESADOS Y REQUISITOS
A2: Proyecto…
A6: Interesado | B6: Requisitos | C6: Valoración de Poder | D6: Valoración de Interés | E6: Estrategia Potencial
A7: Nombre y Apellido (Personas Físicas) Nombre Institucional (Personas Jurídicas) | B7: Descripción de principales expectativas y requisitos exigidos al Proyecto por parte del Interesado | C7: Alto/Medio/Bajo - Positivo/Neutro/Negativo | D7: Alto/Medio/Bajo | E7: Mecanismos tendientes a fomentar que se ejerzan influencias positivas y que no se ejerzan influencias negativas
A23: Observaciones:
A24: Se completa primero la columna de interesados. Una vez completada la misma se trabaja por fila detallando para cada interesado los requisitos, la valoración de impacto y la estrategia potencial.

Sheet ACTIVIDADES Y COSTO
A1: GRILLA DE DEFINICION DE ACTIVIDADES Y COSTOS
A2: =+' INTERESADOS Y REQUISITOS'!A2 -> Proyecto…
A6: N° Orden | B6: Paquete de Trabajo | C6: Actividad | D6: Predecesora | E6: Responsable | F6: Recursos Necesarios | G6: Duración | H6: Período necesario para su realización (Desde - Hasta) | J6: Costo
A7: N° Correlativo | B7: Último nivel de EDT | C7: Descripción de la actividad a ejecutar | D7: N° de Orden de Actividades que deben ejecutarse antes | E7: Responsable de la actividad descripta | F7: Estimación de tipos de recursos necesarios para su realización (RRHH, Bienes, Servicios, Obras, etc) | G7: En Días | H7: Período necesario para su realización (Desde - Hasta) | J7: Estimación de costo de los recursos necesarios para su realización
A8: 1 | I8: =IF(+G8=0,"-",G8+H8) -> -
A9: =+A8+1 -> 2 | I9: =IF(+G9=0,"-",G9+H9) -> -
A10: =+A9+1 -> 3 | I10: =IF(+G10=0,"-",G10+H10) -> -
A11: =+A10+1 -> 4 | I11: =IF(+G11=0,"-",G11+H11) -> -
A12: =+A11+1 -> 5 | I12: =IF(+G12=0,"-",G12+H12) -> -
A13: =+A12+1 -> 6 | I13: =IF(+G13=0,"-",G13+H13) -> -
A14: =+A13+1 -> 7 | I14: =IF(+G14=0,"-",G14+H14) -> -
A15: =+A14+1 -> 8 | I15: =IF(+G15=0,"-",G15+H15) -> -
A16: =+A15+1 -> 9 | I16: =IF(+G16=0,"-",G16+H16) -> -
A17: =+A16+1 -> 10 | I17: =IF(+G17=0,"-",G17+H17) -> -
A18: =+A17+1 -> 11 | I18: =IF(+G18=0,"-",G18+H18) -> -
A19: =+A18+1 -> 12 | I19: =IF(+G19=0,"-",G19+H19) -> -
A20: =+A19+1 -> 13 | I20: =IF(+G20=0,"-",G20+H20) -> -
... A35: =+A34+1 -> 28 | I35: =IF(+G35=0,"-",G35+H35) -> -
A37: Observaciones:
B38: Se completa partir de los Paquetes de Trabajo definidos en el EDT.

Sheet EDT
A1: ESTRUCTURA DE DESGLOSE DEL TRABAJO
A2: =+' INTERESADOS Y REQUISITOS'!A2 -> Proyecto…
A6: =+' INTERESADOS Y REQUISITOS'!A2 -> Proyecto… | B6: NDD 1 | C6: NDD 2 | D6: NDD 3 | E6: NDD 4 | F6: NDD 5
B7: DOCUMENTACION DE PROYECTO | C7: Acta de Constitución
C9: Plan de Gestión
B22: CIERRE DEL PROYECTO | C22: Informe de Lecciones Aprendidas
C23: Acta de Cierre Firmada
C24: Ordenamiento Documental
C25: Publicación y difusión de los resultados
B27: Nivel de Desglose | C27: NDD
B28: Paquete de Trabajo
A30: Observaciones:
A31: Se completa por columna. Una vez finalizado un nivel de desglose/descomposición se pasa al siguiente.

Sheet CRONOGRAMA
A1: CRONOGRAMA
A2: =+'CONTROL DE CAMBIOS'!A2 -> Proyecto…
A5: Paquetes de Trabajo | B5: Mes 1 | C5: Mes 2 | D5: Mes 3 | E5: Mes 4 | F5: Mes 5 | G5: Mes 6 | H5: Mes 7 | I5: Mes 8 | J5: Mes 9 | K5: Mes 10 | L5: Mes 11
B6: 42795 | C6: 42826 | D6: 42856 | E6: 42887 | F6: 42917 | G6: 42948 | H6: 42979 | I6: 43009 | J6: 43040 | K6: 43070 | L6: 43101
A7: Acta de Constitución
A8: Grilla de Interesados y Requisitos
A9: EDT
A10: Grilla de Definición de Actividades
A11: Grilla de Identificación y Análisis de Riesgos
A12: Cronograma
A13: Presupuesto
A14: Modelos de Informes de Avance y Seguimiento
A15: Plan de Comunicación
A16: Acta de Cierre
A29: Informe de Lecciones Aprendidas
A30: Acta de Cierre Documentada
... A35: El Cronograma se completa a partir del EDT y de la planilla de Definición de Actividades.

Sheet RIESGOS
A1: GRILLA DE IDENTIFICACIÓN Y ANÁLISIS DE RIESGOS
A2: =+' INTERESADOS Y REQUISITOS'!A2 -> Proyecto…
A6: Evento de Riesgo | B6: Evidencia de Ocurrencia | C6: Valoración de Impacto | D6: Valoración de Probabilidad | E6: Estrategia de Respuesta
A7: Descripción del Evento | B7: Situaciones que, de ocurrir, podrían evidenciar que un riesgo ocurrió o estaría por ocurrir | C7: Alto/Medio/Bajo - Positivo/Neutro/Negativo | D7: Alta/Media/Baja | E7: Mecanismos tendientes a fomentar que se ejerzan influencias positivas y que no se ejerzan influencias negativas.
A22: Observaciones:
A23: La Grilla de Interesados y la Definición de Actividades son las bases para pensar los posibles problemas u oportunidades que se pueden presentar durante el desarrollo del proyecto.

Sheet COMUNICACIONES
A1: ESQUEMA DE COMUNICACIONES
A2: Proyecto …….
A5: Información Requerida | B5: Interesados | C5: Nivel de Sensibilidad | D5: Formato de Comunicación | E5: Comunicador | F5: Periodicidad
A6: Plan de Gestión | B6: Unidad de Planificación y Control de Gestión, Oficina de Proyectos Especiales y Equipo de Proyecto. | C6: Alto | D6: Documento Excel | E6: Director del proyecto | F6: Al inicio del proyecto o ante cambios
A13: Informes de Avance | B13: Equipo de Proyecto y Áreas involucradas en el Proyecto | C13: Alto | D13: Documento Word - Convertido a PDF | E13: Director del proyecto | F13: Cada 15 días
A20: Minutas de Reunión | B20: Participantes de la Reunión | C20: Medio | D20: Documento Word - Convertido a PDF | E20: Director del proyecto | F20: Según realización de Reuniones
A24: Acta de Cierre | B24: Unidad de Planificación y Control de Gestión, Oficina de Proyectos Especiales, Equipo de Proyectos y Áreas involucradas en el Proyecto | C24: Alto | D24: Documento Word - Convertido a PDF | E24: Director del proyecto | F24: Al finalizarse el proyecto o una etapa
A29: Reuniones | B29: Participantes | C29: Documentos Requeridos | D29: Periodicidad / Duración | E29: Canal | F29: Convocante
A30: Reunión Inicial de Presentación de Proyecto | B30: Equipo de Proyecto y Áreas involucradas en el Proyecto | C30: Resumen integral del Proyecto | D30: Única vez inicio del proyecto - 1 hora | E30: Presencial | F30: Director del proyecto
A33: Reunión de Seguimiento y Avance | B33: Equipo de Proyecto y Áreas involucradas en el Proyecto | C33: Informe de avance del Proyecto | D33: Quincenal - 1/2 hora | E33: Presencial | F33: Director del proyecto
A36: Reuniones a requerimiento | B36: A requerimiento. | C36: A requerimiento | D36: A requerimiento | E36: A requerimiento | F36: Director del proyecto

Sheet CONTRATACIONES
A1: PLANIFICACION DE CONTRATACIONES
A2: =+' INTERESADOS Y REQUISITOS'!A2 -> Proyecto…
A5: Tipo de procedimiento | B5: Area | C5: Fecha estimada de la necesidad | D5: Necesidad / Objeto de la Contratacion | E5: Cantidad | F5: Unidad de Medida | G5: Costo Estimado | H5: Plazo de cumplimiento de la Contratacion
G14: =SUM(G6:G13) -> 0
